torczon.py
torczon-0.0.1.dist-info/LICENSE
torczon-0.0.1.dist-info/METADATA
torczon-0.0.1.dist-info/WHEEL
torczon-0.0.1.dist-info/top_level.txt
torczon-0.0.1.dist-info/RECORD
