Metadata-Version: 2.1
Name: torczon
Version: 0.0.1
Summary: A NLP derivative-free solver using a modified version of the torczon algorithm
Author-email: Mazen Alamir <mazen.alamir@grenoble-inp.fr>
Project-URL: Homepage, https://github.com/mazenalamir/torczon
Project-URL: Issues, https://github.com/mazenalamir/torczon/issues
Keywords: Nonlinear Programming,optimization,derivative free,constrained optimization
Classifier: Programming Language :: Python :: 3
Classifier: License :: OSI Approved :: MIT License
Classifier: Operating System :: OS Independent
Requires-Python: >=3.8
License-File: LICENSE
